[{
  "_id": {
    "$oid": "60c4ba91c020401210a941a0"
  },
  "id": 1001,
  "image": "Client/images/file.jpg",
  "subject": "Physics",
  "price": 50,
  "location": "Geneva",
  "availableInventory": 5
},{
  "_id": {
    "$oid": "60c4ba91c020401210a941a1"
  },
  "id": 1002,
  "image": "che.png",
  "subject": "Chemistry",
  "price": 35,
  "location": "Lagos",
  "availableInventory": 5
},{
  "_id": {
    "$oid": "60c4ba91c020401210a941a2"
  },
  "id": 1003,
  "image": "bio.jpg",
  "subject": "Biology",
  "price": 38,
  "location": "Abuja",
  "availableInventory": 5
},{
  "_id": {
    "$oid": "60c4ba91c020401210a941a3"
  },
  "id": 1004,
  "image": "psy.jpg",
  "subject": "Psychology",
  "price": 39,
  "location": "Ontario",
  "availableInventory": 5
},{
  "_id": {
    "$oid": "60c4ba91c020401210a941a4"
  },
  "id": 1005,
  "image": "geo.png",
  "subject": "Geography",
  "price": 42,
  "location": "Granada",
  "availableInventory": 5
},{
  "_id": {
    "$oid": "60c4ba91c020401210a941a5"
  },
  "id": 1006,
  "image": "zoo.jpg",
  "subject": "Zoology",
  "price": 49,
  "location": "Conackry",
  "availableInventory": 5
},{
  "_id": {
    "$oid": "60c4ba91c020401210a941a6"
  },
  "id": 1007,
  "image": "eng.jpg",
  "subject": "Engineering",
  "price": 38,
  "location": "Munich",
  "availableInventory": 5
},{
  "_id": {
    "$oid": "60c4ba91c020401210a941a7"
  },
  "id": 1008,
  "image": "com.jpg",
  "subject": "Computer",
  "price": 41,
  "location": "Timbuktu",
  "availableInventory": 5
},{
  "_id": {
    "$oid": "60c4ba91c020401210a941a8"
  },
  "id": 1009,
  "image": "mat.jpg",
  "subject": "Mathematics",
  "price": 47,
  "location": "Abuja",
  "availableInventory": 5
},{
  "_id": {
    "$oid": "60c4ba91c020401210a941a9"
  },
  "id": 1010,
  "image": "soc.png",
  "subject": "Sociology",
  "price": 26,
  "location": "Toronto",
  "availableInventory": 5
}]